README.md
setup.py
TwitterFlood/__init__.py
TwitterFlood/base.py
TwitterFlood/start.py
TwitterFlood.egg-info/PKG-INFO
TwitterFlood.egg-info/SOURCES.txt
TwitterFlood.egg-info/dependency_links.txt
TwitterFlood.egg-info/not-zip-safe
TwitterFlood.egg-info/top_level.txt