Metadata-Version: 1.0
Name: TwitterFlood
Version: 0.1
Summary: Flood text for Twitter
Home-page: https://github.com/UtkucanBykl/TwitterFlood
Author: utkucanbykl
Author-email: utkucanbykl@gmail.com
License: MIT
Platform: UNKNOWN
